denfaktorial/__init__.py
denfaktorial/denfaktorial.py
denfaktorial-0.0.1.dist-info/LICENSE
denfaktorial-0.0.1.dist-info/METADATA
denfaktorial-0.0.1.dist-info/WHEEL
denfaktorial-0.0.1.dist-info/top_level.txt
denfaktorial-0.0.1.dist-info/RECORD
