Metadata-Version: 2.1
Name: denfaktorial
Version: 0.0.1
Summary: Menghitung nilai faktorial
Author-email: Danang Eko Nuryanto <danang.eko@bmkg.go.id>
Project-URL: Homepage, https://bmkg.go.id
Classifier: Programming Language :: Python :: 3
Classifier: License :: OSI Approved :: MIT License
Classifier: Operating System :: OS Independent
Requires-Python: >=3.7
License-File: LICENSE
